<?xml version="1.0" encoding="windows-1252" ?>
<!DOCTYPE ViewLink SYSTEM "jbo_03_01.dtd">
<!---->
<ViewLink
  xmlns="http://xmlns.oracle.com/bc4j"
  Name="FkRoleUnitsCoUnitsLink"
  Version="12.2.1.11.57"
  InheritPersonalization="merge"
  EntityAssociation="model.EO.FkRoleUnitsCoUnitsAssoc">
  <ViewLinkDefEnd
    Name="TblCompanyUnitsView"
    Cardinality="1"
    Source="true"
    Owner="model.VO.TblCompanyUnitsView">
    <DesignTime>
      <Attr Name="_isUpdateable" Value="true"/>
      <Attr Name="_finderName" Value="TblCompanyUnitsView"/>
    </DesignTime>
    <AttrArray Name="Attributes">
      <Item Value="model.VO.TblCompanyUnitsView.Id"/>
    </AttrArray>
  </ViewLinkDefEnd>
  <ViewLinkDefEnd
    Name="TblRoleUnitsView"
    Cardinality="-1"
    Owner="model.VO.TblRoleUnitsView">
    <DesignTime>
      <Attr Name="_isUpdateable" Value="true"/>
      <Attr Name="_finderName" Value="TblRoleUnitsView"/>
    </DesignTime>
    <AttrArray Name="Attributes">
      <Item Value="model.VO.TblRoleUnitsView.CompanyUnitsId"/>
    </AttrArray>
  </ViewLinkDefEnd>
</ViewLink>
